{
  "requestId": "REQ-001",
  "answers": [
    {
      "qustionId": "1",
      "answer": null
    },
    {
      "qustionId": "2",
      "answer": "GREEN"
    },
    {
      "qustionId": "3",
      "answer": "No"
    },
    {
      "qustionId": "4",
      "answer": "Yes",
      "nestedAnswers" :[
        {
          "qustionId": "5",
          "answer": "Non Relational",
          "nestedAnswers" :[
            {
              "qustionId": "6",
              "answer": null
            },
            {
              "qustionId": "7",
              "answer": "Neo4j"
            }
          ]
        }
      ]
    },
    {
      "qustionId": "8",
      "answer": "Yes",
      "nestedAnswers": [
        {
          "qustionId": "9",
          "answer": "Yes"
        }
      ]
    },
    {
      "qustionId": "10",
      "answer": "No"
    }
  ]
}